comics/__init__.py
comics/_gocomics.py
comics/exceptions.py
comics/_constants/__init__.py
comics/_constants/_directory.py
comics/_constants/_endpoints.json
comics-0.9.2.dist-info/licenses/LICENSE
comics-0.9.2.dist-info/METADATA
comics-0.9.2.dist-info/WHEEL
comics-0.9.2.dist-info/top_level.txt
comics-0.9.2.dist-info/RECORD
