Metadata-Version: 2.4
Name: comics
Version: 0.9.2
Summary: GoComics API wrapper
Author-email: Ira Horecka <ira89@icloud.com>
License: MIT
Project-URL: Homepage, https://github.com/irahorecka/comics
Classifier: Intended Audience :: Developers
Classifier: Operating System :: OS Independent
Classifier: Programming Language :: Python :: 3.8
Classifier: Programming Language :: Python :: 3.9
Classifier: Programming Language :: Python :: 3.10
Classifier: Programming Language :: Python :: 3.11
Classifier: Programming Language :: Python :: 3.12
Classifier: Programming Language :: Python :: 3.13
Classifier: Topic :: Software Development :: Libraries
Classifier: Topic :: Utilities
Requires-Python: >=3.8
License-File: LICENSE
Requires-Dist: beautifulsoup4<5.0.0,>=4.11.0
Requires-Dist: ipython<9.0.0,>=8.5.0
Requires-Dist: Pillow<12.0.0,>=9.2.0
Requires-Dist: python-dateutil<3.0.0,>=2.8.0
Requires-Dist: requests<3.0.0,>=2.28.0
Requires-Dist: playwright<2.0.0,>1.41.0
Dynamic: license-file
